multivariate_view/__init__.py
multivariate_view/typing.py
multivariate_view/app/__init__.py
multivariate_view/app/app.py
multivariate_view/app/io.py
multivariate_view/app/main.py
multivariate_view/app/volume_view.py
multivariate_view/app/assets/__init__.py
multivariate_view/app/assets/favicon.png
multivariate_view/app/assets/__pycache__/__init__.cpython-311.pyc
multivariate_view/app/compute/__init__.py
multivariate_view/app/compute/bin.py
multivariate_view/app/compute/gbc.py
multivariate_view/app/compute/hsl.py
multivariate_view/module/.gitignore
multivariate_view/module/__init__.py
multivariate_view/module/serve/multivariate_view.umd.js
multivariate_view/widgets/__init__.py
multivariate_view/widgets/radvolviz.py
test/conftest.py
test/requirements.txt
test/test_bin.py
test/test_colors.py
test/test_gbc.py
test/test_data/data10.csv
test/test_output/bins1.npz
test/test_output/bins2.npz
test/test_output/bins3.npz
test/test_output/gbc1.npz
test/test_output/gbc2.npz
test/test_output/gbc3.npz
vue-components/.editorconfig
vue-components/.eslintrc.cjs
vue-components/.gitignore
vue-components/.prettierrc.json
vue-components/package-lock.json
vue-components/package.json
vue-components/vite.config.js
vue-components/node_modules/flatted/python/flatted.py
vue-components/node_modules/flatted/python/test.py
vue-components/node_modules/npm/node_modules/node-gyp/update-gyp.py
vue-components/node_modules/npm/node_modules/node-gyp/gyp/gyp_main.py
vue-components/node_modules/npm/node_modules/node-gyp/gyp/setup.py
vue-components/node_modules/npm/node_modules/node-gyp/gyp/test_gyp.py
vue-components/node_modules/npm/node_modules/node-gyp/gyp/pylib/gyp/MSVSNew.py
vue-components/node_modules/npm/node_modules/node-gyp/gyp/pylib/gyp/MSVSProject.py
vue-components/node_modules/npm/node_modules/node-gyp/gyp/pylib/gyp/MSVSSettings.py
vue-components/node_modules/npm/node_modules/node-gyp/gyp/pylib/gyp/MSVSSettings_test.py
multivariate_view-0.1.3.dist-info/LICENSE
multivariate_view-0.1.3.dist-info/METADATA
multivariate_view-0.1.3.dist-info/WHEEL
multivariate_view-0.1.3.dist-info/entry_points.txt
multivariate_view-0.1.3.dist-info/top_level.txt
multivariate_view-0.1.3.dist-info/RECORD
