Metadata-Version: 2.1
Name: multivariate-view
Version: 0.1.3
Summary: RadVolViz-inspired multivariate volume visualizer using VTK
Author-email: Patrick Avery <patrick.avery@kitware.com>, Sankhesh Jhaveri <sankhesh.jhaveri@kitware.com>, Sebastien Jourdain <sebastien.jourdain@kitware.com>
Maintainer-email: Patrick Avery <patrick.avery@kitware.com>, Sankhesh Jhaveri <sankhesh.jhaveri@kitware.com>, Sebastien Jourdain <sebastien.jourdain@kitware.com>
License: Copyright 2024 Kitware Inc.
Keywords: web,trame,vtk,radvolviz,multivariate,volume
Classifier: Development Status :: 4 - Beta
Classifier: Intended Audience :: Developers
Classifier: License :: OSI Approved :: Apache Software License
Classifier: Programming Language :: Python :: 3
Classifier: Programming Language :: Python :: 3.11
Requires-Python: >=3.10
License-File: LICENSE
Requires-Dist: h5py
Requires-Dist: numba
Requires-Dist: pillow
Requires-Dist: plotly
Requires-Dist: requests
Requires-Dist: scipy
Requires-Dist: trame
Requires-Dist: trame-vtk
Requires-Dist: trame-vuetify
Requires-Dist: trame-plotly
Requires-Dist: vtk
